pyguin/__init__.py
pyguin/__main__.py
pyguin/pyguin.py
pyguin/render_jinja.py
pyguin-0.0.1.dist-info/LICENSE
pyguin-0.0.1.dist-info/METADATA
pyguin-0.0.1.dist-info/WHEEL
pyguin-0.0.1.dist-info/entry_points.txt
pyguin-0.0.1.dist-info/top_level.txt
pyguin-0.0.1.dist-info/RECORD
