Metadata-Version: 2.1
Name: pyguin
Version: 0.0.1
Summary: A minimalistic static site generator intended to be very quick and intuitive to understand and extend
Home-page: https://github.com/airikWarren/pyguin
Author: Airik Warren
Author-email: airikwarren@gmail.com
License: UNKNOWN
Project-URL: Bug Tracker, https://github.com/airikWarren/pyguin/issues
Platform: UNKNOWN
Classifier: Programming Language :: Python :: 3
Classifier: License :: OSI Approved :: MIT License
Classifier: Operating System :: OS Independent
Requires-Python: >=3.6
Requires-Dist: Jinja2
Requires-Dist: click
Requires-Dist: requests
